envninja/__init__.py
envninja/core.py
envninja-0.1.0.dist-info/METADATA
envninja-0.1.0.dist-info/WHEEL
envninja-0.1.0.dist-info/top_level.txt
envninja-0.1.0.dist-info/RECORD
