Metadata-Version: 2.4
Name: envninja
Version: 0.1.0
Summary: A lightweight environment variable manager and validator for Python 🥷
Author-email: Aswin Ganga <aswinganga8@gmail.com>
License: MIT
Project-URL: Homepage, https://github.com/Techy0Ganga/envninja
Project-URL: Source, https://github.com/Techy0Ganga/envninja
Keywords: env,dotenv,config,validator,security,python
Classifier: Development Status :: 3 - Alpha
Classifier: Intended Audience :: Developers
Classifier: License :: OSI Approved :: MIT License
Classifier: Programming Language :: Python :: 3
Classifier: Programming Language :: Python :: 3.7
Classifier: Programming Language :: Python :: 3.8
Classifier: Programming Language :: Python :: 3.9
Classifier: Programming Language :: Python :: 3.10
Classifier: Topic :: Software Development :: Libraries :: Python Modules
Classifier: Operating System :: OS Independent
Requires-Python: >=3.7
Requires-Dist: python-dotenv
